ethoscopy/__init__.py
ethoscopy/analyse.py
ethoscopy/behavpy.py
ethoscopy/behavpy_HMM_class.py
ethoscopy/behavpy_class.py
ethoscopy/behavpy_core.py
ethoscopy/behavpy_draw.py
ethoscopy/behavpy_periodogram_class.py
ethoscopy/behavpy_plotly.py
ethoscopy/behavpy_seaborn.py
ethoscopy/load.py
ethoscopy/metadata_db.py
ethoscopy/misc/__init__.py
ethoscopy/misc/circadian_bars.py
ethoscopy/misc/general_functions.py
ethoscopy/misc/get_HMM.py
ethoscopy/misc/get_tutorials.py
ethoscopy/misc/hmm_functions.py
ethoscopy/misc/periodogram_functions.py
ethoscopy/misc/validate_datetime.py
ethoscopy-2.0.4.dist-info/METADATA
ethoscopy-2.0.4.dist-info/WHEEL
ethoscopy-2.0.4.dist-info/licenses/LICENSE
ethoscopy-2.0.4.dist-info/RECORD
