Metadata-Version: 2.4
Name: ethoscopy
Version: 2.0.4
Summary: "A python based toolkit to download and anlyse data from the Ethoscope hardware system."
Author-email: Lblackhurst29 <lblackhurst29@gmail.com>
License-File: LICENSE
Classifier: Development Status :: 4 - Beta
Classifier: Intended Audience :: Science/Research
Classifier: License :: OSI Approved :: GNU General Public License v3 (GPLv3)
Classifier: Operating System :: OS Independent
Classifier: Programming Language :: Python :: 3
Classifier: Programming Language :: Python :: 3.10
Classifier: Programming Language :: Python :: 3.11
Classifier: Programming Language :: Python :: 3.12
Classifier: Topic :: Scientific/Engineering :: Bio-Informatics
Classifier: Topic :: Scientific/Engineering :: Information Analysis
Requires-Python: <4.0,>=3.10
Requires-Dist: astropy<7.0,>=6.1
Requires-Dist: colour<0.2.0,>=0.1.5
Requires-Dist: hmmlearn<0.4.0,>=0.3.2
Requires-Dist: nbformat<6.0.0,>=5.10.4
Requires-Dist: numpy<3.0.0,>=2.0.0
Requires-Dist: pandas<3.0.0,>=2.2.2
Requires-Dist: plotly<6.0.0,>=5.22.0
Requires-Dist: pywavelets<2.0.0,>=1.6.0
Requires-Dist: seaborn<0.14.0,>=0.13.2
Requires-Dist: tabulate<0.10.0,>=0.9.0
Provides-Extra: dev
Requires-Dist: black<25.0.0,>=24.0.0; extra == 'dev'
Requires-Dist: ipykernel<7.0.0,>=6.29.5; extra == 'dev'
Requires-Dist: isort<6.0.0,>=5.13.0; extra == 'dev'
Requires-Dist: pre-commit<4.0.0,>=3.0.0; extra == 'dev'
Requires-Dist: pytest-cov<6.0.0,>=5.0.0; extra == 'dev'
Requires-Dist: pytest-mock<4.0.0,>=3.12.0; extra == 'dev'
Requires-Dist: pytest-xdist<4.0.0,>=3.5.0; extra == 'dev'
Requires-Dist: pytest<9.0.0,>=8.0.0; extra == 'dev'
Requires-Dist: ruff<1.0.0,>=0.1.0; extra == 'dev'
